awesome_cheap_flights/__init__.py
awesome_cheap_flights/__main__.py
awesome_cheap_flights/cli.py
awesome_cheap_flights/pipeline.py
awesome_cheap_flights-1.0.3.dist-info/licenses/LICENSE
awesome_cheap_flights-1.0.3.dist-info/METADATA
awesome_cheap_flights-1.0.3.dist-info/WHEEL
awesome_cheap_flights-1.0.3.dist-info/entry_points.txt
awesome_cheap_flights-1.0.3.dist-info/top_level.txt
awesome_cheap_flights-1.0.3.dist-info/RECORD
