Metadata-Version: 2.4
Name: awesome-cheap-flights
Version: 1.0.3
Summary: Weekend-hopper toolkit for ICN short-haul scouting
Author: Awesome Cheap Flights Maintainers
License: MIT
Project-URL: homepage, https://github.com/awesome-cheap-flights/awesome-cheap-flights
Project-URL: source, https://github.com/awesome-cheap-flights/awesome-cheap-flights
Project-URL: issues, https://github.com/awesome-cheap-flights/awesome-cheap-flights/issues
Keywords: flights,travel,scraper
Classifier: Programming Language :: Python :: 3
Classifier: License :: OSI Approved :: MIT License
Classifier: Operating System :: OS Independent
Requires-Python: >=3.10
License-File: LICENSE
Requires-Dist: fast-flights>=2.2
Requires-Dist: json5>=0.12.1
Requires-Dist: pyyaml>=6.0.3
Requires-Dist: rich>=13.7
Requires-Dist: typing-extensions>=4.5
Requires-Dist: openpyxl>=3.1
Dynamic: license-file
